concurrentfloodscraper/__init__.py
concurrentfloodscraper/base_controller.py
concurrentfloodscraper/base_worker.py
concurrentfloodscraper/concurrent_flood_scraper.py
concurrentfloodscraper/exceptions.py
concurrentfloodscraper/pubsub.py
concurrentfloodscraper/router.py
concurrentfloodscraper/scraper.py
concurrentfloodscraper/ticker.py
concurrentfloodscraper/url_builder.py
concurrentfloodscraper/wikipedia_demo.py
concurrentfloodscraper-1.0.1.dist-info/DESCRIPTION.rst
concurrentfloodscraper-1.0.1.dist-info/METADATA
concurrentfloodscraper-1.0.1.dist-info/RECORD
concurrentfloodscraper-1.0.1.dist-info/WHEEL
concurrentfloodscraper-1.0.1.dist-info/metadata.json
concurrentfloodscraper-1.0.1.dist-info/top_level.txt
