Metadata-Version: 2.0
Name: concurrentfloodscraper
Version: 1.0.1
Summary: A concurrent flood web scraper.
Home-page: https://github.com/LucasSimpson/ConcurrentFloodScraper
Author: Lucas Simpson
Author-email: lucassimpson05@gmail.com
License: MIT
Keywords: crawl crawler scrape scraper web internet
Platform: UNKNOWN
Classifier: Development Status :: 3 - Alpha
Classifier: Intended Audience :: Developers
Classifier: Topic :: Software Development
Classifier: License :: OSI Approved :: MIT License
Classifier: Programming Language :: Python :: 3
Requires-Dist: requests
